doxtract/__init__.py
doxtract/processor.py
doxtract/utils/__init__.py
doxtract/utils/geometry.py
doxtract/utils/headers.py
doxtract/utils/images.py
doxtract/utils/text.py
doxtract/utils/toc.py
doxtract-0.0.5.dist-info/METADATA
doxtract-0.0.5.dist-info/WHEEL
doxtract-0.0.5.dist-info/top_level.txt
doxtract-0.0.5.dist-info/RECORD
