Metadata-Version: 2.4
Name: doxtract
Version: 0.0.5
Summary: Structured document processor with diagram/image/text extraction and dataset output
Home-page: https://github.com/EthanRyne/Advanced_pdf_extractor
Author: Bhavesh Kumar
Author-email: bhaveshk@gmail.com
Classifier: Development Status :: 3 - Alpha
Classifier: Intended Audience :: Developers
Classifier: Intended Audience :: Science/Research
Classifier: License :: OSI Approved :: MIT License
Classifier: Programming Language :: Python :: 3.9
Classifier: Topic :: Text Processing :: Linguistic
Classifier: Topic :: Scientific/Engineering :: Information Analysis
Requires-Python: >=3.9
Requires-Dist: PyMuPDF>=1.22.0
Requires-Dist: tqdm>=4.60.0
Requires-Dist: datasets>=2.0.0
Dynamic: author
Dynamic: author-email
Dynamic: classifier
Dynamic: description
Dynamic: description-content-type
Dynamic: home-page
Dynamic: requires-dist
Dynamic: requires-python
Dynamic: summary
